README
setup.py
cfscrape/__init__.py
cfscrape/cfscrape.py
cfscrapefork.egg-info/PKG-INFO
cfscrapefork.egg-info/SOURCES.txt
cfscrapefork.egg-info/dependency_links.txt
cfscrapefork.egg-info/requires.txt
cfscrapefork.egg-info/top_level.txt