Metadata-Version: 1.0
Name: cfscrapefork
Version: 1.0.2
Summary: cfscrape
Home-page: http://pypi.python.org/pypi/cf-scrape-fork/
Author: Steven Veshkini
Author-email: sveshkini@berkeley.edu
License: UNKNOWN
Platform: UNKNOWN
